jrtimeman/__init__.py
jrtimeman/base.py
jrtimeman/credentials.py
jrtimeman/errors.py
jrtimeman/utils.py
jrtimeman-0.2.13.dist-info/entry_points.txt
jrtimeman-0.2.13.dist-info/WHEEL
jrtimeman-0.2.13.dist-info/METADATA
jrtimeman-0.2.13.dist-info/RECORD
