Metadata-Version: 2.1
Name: jrtimeman
Version: 0.2.13
Summary: Jumping Rivers: Time Management
Author: Jack Walton
Author-email: jwalton3141@gmail.com
Requires-Python: >=3.7.1,<3.11
Classifier: Programming Language :: Python :: 3
Classifier: Programming Language :: Python :: 3.8
Requires-Dist: beautiful-date (>=2.0.0,<3.0.0)
Requires-Dist: gcsa (>=1.2.0,<2.0.0)
Requires-Dist: google (>=3.0.0,<4.0.0)
Requires-Dist: matplotlib (>=3.4.3,<4.0.0)
Requires-Dist: numpy (>=1.21.2,<2.0.0)
Requires-Dist: pandas (>=1.3.2,<2.0.0)
Requires-Dist: tabulate (>=0.8.9,<0.9.0)
